syntaxcomp/__init__.py
syntaxcomp/complexity.py
syntaxcomp/example.py
syntaxcomp-0.0.1.dist-info/LICENSE
syntaxcomp-0.0.1.dist-info/METADATA
syntaxcomp-0.0.1.dist-info/WHEEL
syntaxcomp-0.0.1.dist-info/top_level.txt
syntaxcomp-0.0.1.dist-info/RECORD
