Metadata-Version: 2.1
Name: syntaxcomp
Version: 0.0.1
Summary: A package for extracting syntactic complexity measures from CoNLL-U annotations.
Author-email: Elizaveta Klykova <lizaklyk@gmail.com>
Maintainer-email: Elizaveta Klykova <lizaklyk@gmail.com>
Project-URL: Repository, https://github.com/eaklykova/syntaxcomp
Project-URL: Issues, https://github.com/eaklykova/syntaxcomp/issues
Keywords: complexity,syntax,syntactic complexity,text complexity,conllu,udpipe,clause extraction,sentence segmentation,clause segmentation
Classifier: Development Status :: 3 - Alpha
Classifier: Programming Language :: Python :: 3
Classifier: Programming Language :: Python :: 3.9
Classifier: License :: OSI Approved :: GNU General Public License v3 (GPLv3)
Classifier: Operating System :: OS Independent
Requires-Python: >=3.9
License-File: LICENSE
Requires-Dist: conllu ~=4.5.3
Requires-Dist: textdistance ~=4.6.2
